{
  "lastUpdated": "2026-04-23",
  "data": {   
    "activeNodes": 3845,
    "activeValidators": 95,
    "dailyValidations": 18257,
    
    "dexLiquidity": 1082229,
    "cexLocked": 3070697,
    "teamWallet": 1604553,
    "polygonMNW": 7123083,
    "ethereumMNW": 28026776,
    "lostTokens": 500000,
    
    "nodes3m": 100,
    "nodes6m": 382,
    "nodes12m": 3363,
    
    "reward3m": 0.06,
    "reward6m": 0.08,
    "reward12m": 0.10,
    
    "totalSupply": 47897218,
    "stakePerNode": 1800
  }
}
