{
  "lastUpdated": "2026-01-27",
  "data": {
    "activeNodes": 4431,
    "activeValidators": 109,
    "dailyValidations": 18584,
    
    "dexLiquidity": 1301347,
    "cexLocked": 3380937,
    "teamWallet": 1725034,
    "polygonMNW": 5523430,
    "ethereumMNW": 27764651,
    "lostTokens": 500000,
    
    "nodes3m": 445,
    "nodes6m": 357,
    "nodes12m": 3628,
    
    "reward3m": 0.06,
    "reward6m": 0.08,
    "reward12m": 0.10,
    
    "totalSupply": 47897218,
    "stakePerNode": 1800
  }
}
